GoutongdeYishu/README.md
GoutongdeYishu/__init__.py
GoutongdeYishu/__main__.py
GoutongdeYishu/file.epub
GoutongdeYishu/index.html
GoutongdeYishu/css/__init__.py
GoutongdeYishu/css/annotations.css
GoutongdeYishu/css/main.css
GoutongdeYishu/css/normalize.css
GoutongdeYishu/css/popup.css
GoutongdeYishu/font/__init__.py
GoutongdeYishu/font/fontello.eot
GoutongdeYishu/font/fontello.svg
GoutongdeYishu/font/fontello.ttf
GoutongdeYishu/font/fontello.woff
GoutongdeYishu/img/__init__.py
GoutongdeYishu/img/annotator-glyph-sprite.png
GoutongdeYishu/img/annotator-icon-sprite.png
GoutongdeYishu/img/apple-touch-icon.png
GoutongdeYishu/img/cancelfullscreen.png
GoutongdeYishu/img/close.png
GoutongdeYishu/img/fullscreen.png
GoutongdeYishu/img/loader.gif
GoutongdeYishu/img/menu-icon.png
GoutongdeYishu/img/save.png
GoutongdeYishu/img/saved.png
GoutongdeYishu/img/settings-s.png
GoutongdeYishu/img/settings.png
GoutongdeYishu/img/star.png
GoutongdeYishu/js/__init__.py
GoutongdeYishu/js/epub.js
GoutongdeYishu/js/epub.min.js
GoutongdeYishu/js/epub.min.map
GoutongdeYishu/js/hooks.min.js
GoutongdeYishu/js/hooks.min.map
GoutongdeYishu/js/reader.js
GoutongdeYishu/js/reader.js.map
GoutongdeYishu/js/reader.min.js
GoutongdeYishu/js/reader.min.map
GoutongdeYishu/js/hooks/__init__.py
GoutongdeYishu/js/hooks/extensions/__init__.py
GoutongdeYishu/js/hooks/extensions/highlight.js
GoutongdeYishu/js/libs/__init__.py
GoutongdeYishu/js/libs/jquery.min.js
GoutongdeYishu/js/libs/localforage.min.js
GoutongdeYishu/js/libs/screenfull.js
GoutongdeYishu/js/libs/screenfull.min.js
GoutongdeYishu/js/libs/zip.min.js
GoutongdeYishu/js/plugins/__init__.py
GoutongdeYishu/js/plugins/hypothesis.js
GoutongdeYishu/js/plugins/search.js
goutongde_yishu-2022.10.11.0.dist-info/METADATA
goutongde_yishu-2022.10.11.0.dist-info/WHEEL
goutongde_yishu-2022.10.11.0.dist-info/entry_points.txt
goutongde_yishu-2022.10.11.0.dist-info/top_level.txt
goutongde_yishu-2022.10.11.0.dist-info/RECORD
